{
  "last_updated": "2026-05-24T02:49:58.843582+00:00",
  "source": "PandaScore API",
  "note": "VRS очки приблизительные — PandaScore не публикует официальный VRS Valve",
  "teams": [
    {
      "global_rank": 1,
      "name": "Keyd",
      "acronym": "Keyd",
      "flag": "🇧🇷",
      "region": "americas",
      "points": 2500,
      "qualified": true,
      "pandascore_id": 3225
    },
    {
      "global_rank": 2,
      "name": "ex-PeeP",
      "acronym": null,
      "flag": "🏳",
      "region": "europe",
      "points": 2390,
      "qualified": true,
      "pandascore_id": 138055
    },
    {
      "global_rank": 3,
      "name": "Bebop",
      "acronym": "BBP",
      "flag": "🇷🇺",
      "region": "europe",
      "points": 2280,
      "qualified": true,
      "pandascore_id": 137701
    },
    {
      "global_rank": 4,
      "name": "ASTRAL",
      "acronym": "ASTR",
      "flag": "🏳",
      "region": "europe",
      "points": 2170,
      "qualified": true,
      "pandascore_id": 137440
    },
    {
      "global_rank": 5,
      "name": "Bushido Wildcats",
      "acronym": "BW",
      "flag": "🇹🇷",
      "region": "asia",
      "points": 2060,
      "qualified": true,
      "pandascore_id": 136934
    },
    {
      "global_rank": 6,
      "name": "ex-Zero Tenacity",
      "acronym": null,
      "flag": "🏳",
      "region": "asia",
      "points": 1950,
      "qualified": true,
      "pandascore_id": 137703
    },
    {
      "global_rank": 7,
      "name": "UNiTY esports",
      "acronym": "UNiTY",
      "flag": "🇸🇰",
      "region": "europe",
      "points": 1840,
      "qualified": true,
      "pandascore_id": 133063
    },
    {
      "global_rank": 8,
      "name": "ALGO Esports",
      "acronym": "ALGO",
      "flag": "🇺🇦",
      "region": "europe",
      "points": 1730,
      "qualified": true,
      "pandascore_id": 136539
    },
    {
      "global_rank": 9,
      "name": "Hashiras",
      "acronym": null,
      "flag": "🏳",
      "region": "europe",
      "points": 1620,
      "qualified": false,
      "pandascore_id": 138236
    },
    {
      "global_rank": 10,
      "name": "EC BANGA",
      "acronym": null,
      "flag": "🏳",
      "region": "asia",
      "points": 1510,
      "qualified": false,
      "pandascore_id": 129922
    },
    {
      "global_rank": 11,
      "name": "SAW",
      "acronym": "SAW",
      "flag": "🇵🇹",
      "region": "europe",
      "points": 1400,
      "qualified": false,
      "pandascore_id": 126738
    },
    {
      "global_rank": 12,
      "name": "Julie&cie",
      "acronym": "JUL",
      "flag": "🏳",
      "region": "europe",
      "points": 1290,
      "qualified": false,
      "pandascore_id": 138612
    },
    {
      "global_rank": 13,
      "name": "MANA eSports",
      "acronym": "MANA",
      "flag": "🏳",
      "region": "europe",
      "points": 1180,
      "qualified": false,
      "pandascore_id": 137080
    },
    {
      "global_rank": 14,
      "name": "Invicta",
      "acronym": "Invicta",
      "flag": "🏳",
      "region": "europe",
      "points": 1070,
      "qualified": false,
      "pandascore_id": 137951
    },
    {
      "global_rank": 15,
      "name": "Leo Team",
      "acronym": "Leo",
      "flag": "🇺🇦",
      "region": "europe",
      "points": 960,
      "qualified": false,
      "pandascore_id": 133269
    },
    {
      "global_rank": 16,
      "name": "Eternal 21",
      "acronym": null,
      "flag": "🇫🇮",
      "region": "europe",
      "points": 850,
      "qualified": false,
      "pandascore_id": 138713
    },
    {
      "global_rank": 17,
      "name": "Rune Eaters",
      "acronym": "RE",
      "flag": "🏳",
      "region": "europe",
      "points": 740,
      "qualified": false,
      "pandascore_id": 132927
    },
    {
      "global_rank": 18,
      "name": "CYBERSHOKE Prospects",
      "acronym": "CSH.P",
      "flag": "🇷🇺",
      "region": "europe",
      "points": 630,
      "qualified": false,
      "pandascore_id": 137500
    },
    {
      "global_rank": 19,
      "name": "95 Vikings",
      "acronym": null,
      "flag": "🏳",
      "region": "europe",
      "points": 520,
      "qualified": false,
      "pandascore_id": 138711
    },
    {
      "global_rank": 20,
      "name": "STATE",
      "acronym": "STA",
      "flag": "🇩🇰",
      "region": "europe",
      "points": 410,
      "qualified": false,
      "pandascore_id": 137861
    },
    {
      "global_rank": 21,
      "name": "Fortress",
      "acronym": "FOR",
      "flag": "🇩🇰",
      "region": "europe",
      "points": 300,
      "qualified": false,
      "pandascore_id": 137953
    },
    {
      "global_rank": 22,
      "name": "Strael-Bora",
      "acronym": "S-B",
      "flag": "🏳",
      "region": "europe",
      "points": 190,
      "qualified": false,
      "pandascore_id": 137589
    },
    {
      "global_rank": 23,
      "name": "Sashi Academy",
      "acronym": "SASHI.A",
      "flag": "🇩🇰",
      "region": "europe",
      "points": 80,
      "qualified": false,
      "pandascore_id": 133941
    },
    {
      "global_rank": 24,
      "name": "100 Thieves",
      "acronym": "100T",
      "flag": "🇺🇸",
      "region": "americas",
      "points": 50,
      "qualified": false,
      "pandascore_id": 126452
    },
    {
      "global_rank": 25,
      "name": "Millennium Esports",
      "acronym": "ME",
      "flag": "🏳",
      "region": "europe",
      "points": 50,
      "qualified": false,
      "pandascore_id": 137470
    },
    {
      "global_rank": 26,
      "name": "Persona Grata",
      "acronym": "PG",
      "flag": "🏳",
      "region": "europe",
      "points": 50,
      "qualified": false,
      "pandascore_id": 136335
    },
    {
      "global_rank": 27,
      "name": "Monki Flip",
      "acronym": null,
      "flag": "🇵🇱",
      "region": "europe",
      "points": 50,
      "qualified": false,
      "pandascore_id": 138714
    },
    {
      "global_rank": 28,
      "name": "MIBR Academy",
      "acronym": "MIBR.A",
      "flag": "🇧🇷",
      "region": "americas",
      "points": 50,
      "qualified": false,
      "pandascore_id": 129800
    },
    {
      "global_rank": 29,
      "name": "Sharks",
      "acronym": "SHK",
      "flag": "🇧🇷",
      "region": "americas",
      "points": 50,
      "qualified": false,
      "pandascore_id": 3260
    },
    {
      "global_rank": 30,
      "name": "Inner Circle Esports",
      "acronym": "ICE",
      "flag": "🏳",
      "region": "europe",
      "points": 50,
      "qualified": false,
      "pandascore_id": 136497
    },
    {
      "global_rank": 31,
      "name": "Rebels Gaming",
      "acronym": "RBLS",
      "flag": "🇵🇱",
      "region": "europe",
      "points": 50,
      "qualified": false,
      "pandascore_id": 134251
    },
    {
      "global_rank": 32,
      "name": "A Great Chaos",
      "acronym": null,
      "flag": "🏳",
      "region": "europe",
      "points": 50,
      "qualified": false,
      "pandascore_id": 138676
    },
    {
      "global_rank": 33,
      "name": "brazylijski luz",
      "acronym": "BL",
      "flag": "🇵🇱",
      "region": "europe",
      "points": 50,
      "qualified": false,
      "pandascore_id": 132679
    },
    {
      "global_rank": 34,
      "name": "Atreides",
      "acronym": null,
      "flag": "🏳",
      "region": "europe",
      "points": 50,
      "qualified": false,
      "pandascore_id": 138026
    },
    {
      "global_rank": 35,
      "name": "ENCE",
      "acronym": "ENCE",
      "flag": "🇫🇮",
      "region": "europe",
      "points": 50,
      "qualified": false,
      "pandascore_id": 3251
    },
    {
      "global_rank": 36,
      "name": "Misa Esports",
      "acronym": "MISA",
      "flag": "🇹🇷",
      "region": "asia",
      "points": 50,
      "qualified": false,
      "pandascore_id": 137075
    },
    {
      "global_rank": 37,
      "name": "TNC",
      "acronym": "TNC",
      "flag": "🇵🇱",
      "region": "europe",
      "points": 50,
      "qualified": false,
      "pandascore_id": 137416
    },
    {
      "global_rank": 38,
      "name": "Lilmix",
      "acronym": "LILMIX",
      "flag": "🇸🇪",
      "region": "europe",
      "points": 50,
      "qualified": false,
      "pandascore_id": 126417
    },
    {
      "global_rank": 39,
      "name": "Young Ninjas",
      "acronym": "YN",
      "flag": "🇸🇪",
      "region": "europe",
      "points": 50,
      "qualified": false,
      "pandascore_id": 128327
    },
    {
      "global_rank": 40,
      "name": "WAZABI",
      "acronym": "WAZ",
      "flag": "🇩🇰",
      "region": "europe",
      "points": 50,
      "qualified": false,
      "pandascore_id": 137950
    },
    {
      "global_rank": 41,
      "name": "Entropy",
      "acronym": null,
      "flag": "🇩🇪",
      "region": "europe",
      "points": 50,
      "qualified": false,
      "pandascore_id": 128258
    },
    {
      "global_rank": 42,
      "name": "Project 91",
      "acronym": null,
      "flag": "🏳",
      "region": "europe",
      "points": 50,
      "qualified": false,
      "pandascore_id": 138478
    },
    {
      "global_rank": 43,
      "name": "Oramond",
      "acronym": "ORM",
      "flag": "🏳",
      "region": "europe",
      "points": 50,
      "qualified": false,
      "pandascore_id": 137458
    },
    {
      "global_rank": 44,
      "name": "GenOne",
      "acronym": "G1",
      "flag": "🇫🇷",
      "region": "europe",
      "points": 50,
      "qualified": false,
      "pandascore_id": 128519
    },
    {
      "global_rank": 45,
      "name": "Donstu Esports",
      "acronym": "DNT",
      "flag": "🇷🇺",
      "region": "europe",
      "points": 50,
      "qualified": false,
      "pandascore_id": 135981
    },
    {
      "global_rank": 46,
      "name": "HEROIC Academy",
      "acronym": "HERO.A",
      "flag": "🇳🇴",
      "region": "europe",
      "points": 50,
      "qualified": false,
      "pandascore_id": 136815
    },
    {
      "global_rank": 47,
      "name": "95 Vikings Female",
      "acronym": "95V.F",
      "flag": "🏳",
      "region": "europe",
      "points": 50,
      "qualified": false,
      "pandascore_id": 137516
    },
    {
      "global_rank": 48,
      "name": "eternal premium",
      "acronym": "EP",
      "flag": "🇷🇺",
      "region": "europe",
      "points": 50,
      "qualified": false,
      "pandascore_id": 135978
    },
    {
      "global_rank": 49,
      "name": "Clair Obscur",
      "acronym": "CO",
      "flag": "🇫🇷",
      "region": "europe",
      "points": 50,
      "qualified": false,
      "pandascore_id": 138611
    },
    {
      "global_rank": 50,
      "name": "XCLAN",
      "acronym": null,
      "flag": "🇸🇪",
      "region": "europe",
      "points": 50,
      "qualified": false,
      "pandascore_id": 138712
    }
  ]
}